datafacts/.DS_Store
datafacts/__init__.py
datafacts/generate_img.py
datafacts/fonts/OpenSans-Bold.ttf
datafacts/fonts/OpenSans-Light.ttf
datafacts/fonts/OpenSans-Medium.ttf
datafacts/templates/data_facts.html
datafacts-0.0.10.dist-info/LICENSE
datafacts-0.0.10.dist-info/METADATA
datafacts-0.0.10.dist-info/WHEEL
datafacts-0.0.10.dist-info/top_level.txt
datafacts-0.0.10.dist-info/RECORD
