Metadata-Version: 2.1
Name: datafacts
Version: 0.0.10
Summary: Quickly generate an image with population-level facts about your dataset
Home-page: https://github.com/MedleyLabs/datafacts
Author: Eric Yates
Author-email: eric@medleyagency.com
License: MIT License        
Platform: UNKNOWN
License-File: LICENSE
Requires-Dist: pandas
Requires-Dist: Pillow
